{
  "sections": {
    "main": {
      "type": "producto",
      "blocks": {
        "title": {
          "type": "title",
          "settings": {
          }
        },
        "caption": {
          "type": "text",
          "settings": {
            "text": "{{ product.metafields.descriptors.subtitle.value }}",
            "text_style": "subtitle"
          }
        },
        "description": {
          "type": "description",
          "settings": {
          }
        },
        "price": {
          "type": "price",
          "settings": {
          }
        },
        "quantity_selector": {
          "type": "quantity_selector",
          "settings": {
          }
        },
        "custom_options_tkBiJg": {
          "type": "custom_options",
          "settings": {
            "custom_options": ""
          }
        },
        "buy_buttons": {
          "type": "buy_buttons",
          "settings": {
            "show_dynamic_checkout": true,
            "show_gift_card_recipient": true
          }
        }
      },
      "block_order": [
        "title",
        "caption",
        "description",
        "price",
        "quantity_selector",
        "custom_options_tkBiJg",
        "buy_buttons"
      ],
      "settings": {
        "enable_sticky_info": true,
        "color_scheme": "",
        "media_size": "large",
        "constrain_to_viewport": true,
        "media_fit": "contain",
        "gallery_layout": "stacked",
        "media_position": "left",
        "image_zoom": "lightbox",
        "mobile_thumbnails": "hide",
        "hide_variants": true,
        "enable_video_looping": false,
        "padding_top": 36,
        "padding_bottom": 12
      }
    }
  },
  "order": [
    "main"
  ]
}
